gem/__init__.py
gem/gem.py
gem/gem_utils.py
gem/gem_wrapper.py
gem_torch-1.0.1.dist-info/LICENSE
gem_torch-1.0.1.dist-info/METADATA
gem_torch-1.0.1.dist-info/WHEEL
gem_torch-1.0.1.dist-info/top_level.txt
gem_torch-1.0.1.dist-info/RECORD
