Metadata-Version: 2.1
Name: gem-torch
Version: 1.0.1
Summary: GEM
Home-page: https://github.com/WalBouss/GEM
Author: Walid Bousselham, Felix Petersen, Vittorio Ferrari, Hilde Kuehne
Author-email: 
Keywords: CLIP pretrained
Classifier: Development Status :: 3 - Alpha
Classifier: Intended Audience :: Education
Classifier: Intended Audience :: Science/Research
Classifier: License :: OSI Approved :: Apache Software License
Classifier: Programming Language :: Python :: 3.7
Classifier: Programming Language :: Python :: 3.8
Classifier: Programming Language :: Python :: 3.9
Classifier: Programming Language :: Python :: 3.10
Classifier: Topic :: Scientific/Engineering
Classifier: Topic :: Scientific/Engineering :: Artificial Intelligence
Classifier: Topic :: Software Development
Classifier: Topic :: Software Development :: Libraries
Classifier: Topic :: Software Development :: Libraries :: Python Modules
Requires-Python: >=3.7
License-File: LICENSE
Requires-Dist: torch >=1.9.0
Requires-Dist: torchvision
Requires-Dist: regex
Requires-Dist: ftfy
Requires-Dist: tqdm
Requires-Dist: huggingface-hub
Requires-Dist: sentencepiece
Requires-Dist: protobuf
Requires-Dist: timm
Requires-Dist: einops
Requires-Dist: open-clip-torch
Requires-Dist: opencv-python
Requires-Dist: matplotlib
Requires-Dist: numpy
Requires-Dist: requests
